oe/__init__.py
oe/__main__.py
oe/_core.py
oe/benchmark.py
oe/cli.py
oe/loader.py
oe/quant.py
oe/runtime.py
openvino_easy-1.0.0.dist-info/METADATA
openvino_easy-1.0.0.dist-info/WHEEL
openvino_easy-1.0.0.dist-info/entry_points.txt
openvino_easy-1.0.0.dist-info/RECORD
