Metadata-Version: 2.4
Name: openvino-easy
Version: 1.0.0
Summary: Framework-agnostic Python wrapper for OpenVINO 2025
Project-URL: Homepage, https://github.com/example/openvino-easy
Project-URL: Documentation, https://openvino-easy.readthedocs.io
Project-URL: Repository, https://github.com/example/openvino-easy.git
Project-URL: Bug Tracker, https://github.com/example/openvino-easy/issues
Project-URL: Changelog, https://github.com/example/openvino-easy/blob/main/CHANGELOG.md
Author-email: OpenVINO-Easy Contributors <info@example.com>
Maintainer-email: OpenVINO-Easy Contributors <info@example.com>
License: Apache-2.0
Keywords: ai,inference,openvino,optimization,quantization
Classifier: Development Status :: 5 - Production/Stable
Classifier: Intended Audience :: Developers
Classifier: License :: OSI Approved :: Apache Software License
Classifier: Programming Language :: Python :: 3
Classifier: Programming Language :: Python :: 3.9
Classifier: Programming Language :: Python :: 3.10
Classifier: Programming Language :: Python :: 3.11
Classifier: Programming Language :: Python :: 3.12
Classifier: Topic :: Scientific/Engineering :: Artificial Intelligence
Classifier: Topic :: Software Development :: Libraries :: Python Modules
Requires-Python: >=3.9
Requires-Dist: huggingface-hub>=0.23.0
Requires-Dist: numpy>=1.21.0
Requires-Dist: tqdm>=4.64.0
Provides-Extra: all
Requires-Dist: black>=22.0.0; extra == 'all'
Requires-Dist: colorama>=0.4.0; extra == 'all'
Requires-Dist: datasets>=2.10.0; extra == 'all'
Requires-Dist: diffusers>=0.21.0; extra == 'all'
Requires-Dist: flake8>=5.0.0; extra == 'all'
Requires-Dist: isort>=5.10.0; extra == 'all'
Requires-Dist: librosa>=0.10.0; extra == 'all'
Requires-Dist: mypy>=0.991; extra == 'all'
Requires-Dist: myst-parser>=0.18.0; extra == 'all'
Requires-Dist: nncf<2.16.0,>=2.15.0; extra == 'all'
Requires-Dist: onnx>=1.12.0; extra == 'all'
Requires-Dist: onnxruntime>=1.12.0; extra == 'all'
Requires-Dist: openvino<2026.0.0,>=2025.2.0; extra == 'all'
Requires-Dist: optimum[openvino]>=1.14.0; extra == 'all'
Requires-Dist: pillow>=8.3.0; extra == 'all'
Requires-Dist: pre-commit>=2.20.0; extra == 'all'
Requires-Dist: pytest-cov>=4.0.0; extra == 'all'
Requires-Dist: pytest>=7.0.0; extra == 'all'
Requires-Dist: soundfile>=0.12.0; extra == 'all'
Requires-Dist: sphinx-rtd-theme>=1.0.0; extra == 'all'
Requires-Dist: sphinx>=5.0.0; extra == 'all'
Requires-Dist: tokenizers>=0.13.0; extra == 'all'
Requires-Dist: transformers>=4.25.0; extra == 'all'
Provides-Extra: audio
Requires-Dist: librosa>=0.10.0; extra == 'audio'
Requires-Dist: soundfile>=0.12.0; extra == 'audio'
Provides-Extra: cli
Requires-Dist: colorama>=0.4.0; extra == 'cli'
Provides-Extra: cpu
Requires-Dist: openvino<2026.0.0,>=2025.2.0; extra == 'cpu'
Provides-Extra: datasets
Requires-Dist: datasets>=2.10.0; extra == 'datasets'
Requires-Dist: pillow>=8.3.0; extra == 'datasets'
Provides-Extra: dev
Requires-Dist: black>=22.0.0; extra == 'dev'
Requires-Dist: colorama>=0.4.0; extra == 'dev'
Requires-Dist: flake8>=5.0.0; extra == 'dev'
Requires-Dist: isort>=5.10.0; extra == 'dev'
Requires-Dist: mypy>=0.991; extra == 'dev'
Requires-Dist: pre-commit>=2.20.0; extra == 'dev'
Requires-Dist: pytest-cov>=4.0.0; extra == 'dev'
Requires-Dist: pytest>=7.0.0; extra == 'dev'
Provides-Extra: docs
Requires-Dist: myst-parser>=0.18.0; extra == 'docs'
Requires-Dist: sphinx-rtd-theme>=1.0.0; extra == 'docs'
Requires-Dist: sphinx>=5.0.0; extra == 'docs'
Provides-Extra: full
Requires-Dist: nncf<2.16.0,>=2.15.0; extra == 'full'
Requires-Dist: openvino<2026.0.0,>=2025.2.0; extra == 'full'
Requires-Dist: optimum[openvino]>=1.14.0; extra == 'full'
Provides-Extra: gpu
Requires-Dist: openvino<2026.0.0,>=2025.2.0; extra == 'gpu'
Provides-Extra: npu
Requires-Dist: openvino<2026.0.0,>=2025.2.0; extra == 'npu'
Provides-Extra: onnx
Requires-Dist: onnx>=1.12.0; extra == 'onnx'
Requires-Dist: onnxruntime>=1.12.0; extra == 'onnx'
Provides-Extra: quant
Requires-Dist: nncf<2.16.0,>=2.15.0; extra == 'quant'
Requires-Dist: openvino<2026.0.0,>=2025.2.0; extra == 'quant'
Provides-Extra: runtime
Requires-Dist: openvino<2026.0.0,>=2025.2.0; extra == 'runtime'
Provides-Extra: stable-diffusion
Requires-Dist: diffusers>=0.21.0; extra == 'stable-diffusion'
Requires-Dist: optimum[openvino]>=1.14.0; extra == 'stable-diffusion'
Requires-Dist: transformers>=4.25.0; extra == 'stable-diffusion'
Provides-Extra: text
Requires-Dist: tokenizers>=0.13.0; extra == 'text'
Requires-Dist: transformers>=4.25.0; extra == 'text'
